octoprint_mfa_totp/__init__.py
octoprint_mfa_totp/static/clientjs/mfa_totp.js
octoprint_mfa_totp/static/js/mfa_totp.js
octoprint_mfa_totp/templates/mfa_totp.jinja2
octoprint_mfa_totp/templates/mfa_totp_mfa_login.jinja2
octoprint_mfa_totp/templates/mfa_totp_usersettings_mfa.jinja2
octoprint_mfa_totp/translations/de/LC_MESSAGES/messages.mo
octoprint_mfa_totp/translations/de/LC_MESSAGES/messages.po
OctoPrint_MfaTotp-1.0.0.dist-info/METADATA
OctoPrint_MfaTotp-1.0.0.dist-info/WHEEL
OctoPrint_MfaTotp-1.0.0.dist-info/entry_points.txt
OctoPrint_MfaTotp-1.0.0.dist-info/top_level.txt
OctoPrint_MfaTotp-1.0.0.dist-info/RECORD
